<annotation>
	<folder>dataset2</folder>
	<filename>images (17).jpg</filename>
	<path>/home/isaac/Isaac/Xira/CFE_data_extraction/dataset2/images (17).jpg</path>
	<source>
		<database>Unknown</database>
	</source>
	<size>
		<width>318</width>
		<height>159</height>
		<depth>3</depth>
	</size>
	<segmented>0</segmented>
	<object>
		<name>telmex</name>
		<pose>Unspecified</pose>
		<truncated>0</truncated>
		<difficult>0</difficult>
		<bndbox>
			<xmin>13</xmin>
			<ymin>63</ymin>
			<xmax>88</xmax>
			<ymax>119</ymax>
		</bndbox>
	</object>
</annotation>
